flask_alchemydumps/__init__.py
flask_alchemydumps/autoclean.py
flask_alchemydumps/backup.py
flask_alchemydumps/cli.py
flask_alchemydumps/confirm.py
flask_alchemydumps/database.py
flask_alchemydumps-0.0.13.dist-info/LICENSE
flask_alchemydumps-0.0.13.dist-info/WHEEL
flask_alchemydumps-0.0.13.dist-info/METADATA
flask_alchemydumps-0.0.13.dist-info/RECORD
