Metadata-Version: 2.1
Name: flask-alchemydumps
Version: 0.0.13
Summary: SQLAlchemy backup/dump tool for Flask
Home-page: https://github.com/cuducos/alchemydumps
License: MIT
Keywords: backup,sqlalchemy,flask,restore,ftp
Author: Eduardo Cuducos
Author-email: cuducos@users.noreply.github.com
Requires-Python: >=3.6.2,<3.10.0
Classifier: Development Status :: 3 - Alpha
Classifier: Framework :: Flask
Classifier: Intended Audience :: Developers
Classifier: License :: OSI Approved :: MIT License
Classifier: Programming Language :: Python :: 3
Classifier: Programming Language :: Python :: 3.6
Classifier: Programming Language :: Python :: 3.7
Classifier: Programming Language :: Python :: 3.8
Classifier: Programming Language :: Python :: 3.9
Classifier: Topic :: Database
Classifier: Topic :: System :: Archiving :: Backup
Classifier: Topic :: Utilities
Requires-Dist: Flask (>=1.0.0)
Requires-Dist: Flask-SQLAlchemy (>=2.4.1,<3.0.0)
Requires-Dist: python-decouple (>=3.3,<4.0)
Project-URL: Repository, https://github.com/cuducos/alchemydumps
